ancientMetagenomeDirCheck/__init__.py
ancientMetagenomeDirCheck/cli.py
ancientMetagenomeDirCheck/exceptions.py
ancientMetagenomeDirCheck/main.py
ancientMetagenomeDirCheck-1.3.dist-info/LICENSE
ancientMetagenomeDirCheck-1.3.dist-info/METADATA
ancientMetagenomeDirCheck-1.3.dist-info/WHEEL
ancientMetagenomeDirCheck-1.3.dist-info/entry_points.txt
ancientMetagenomeDirCheck-1.3.dist-info/top_level.txt
ancientMetagenomeDirCheck-1.3.dist-info/RECORD
