Metadata-Version: 2.1
Name: ancientMetagenomeDirCheck
Version: 1.3
Summary: Performs validity check of ancientMetagenomeDir datasets
Home-page: https://github.com/SPAAM-workshop/ancientMetagenomeDirCheck
License: GNU-GPLv3
Platform: UNKNOWN
Requires-Python: >=3.6
Requires-Dist: click
Requires-Dist: pandas
Requires-Dist: jsonschema
Requires-Dist: rich
